pyxiv/__init__.py
pyxiv/constants.py
pyxiv/core.py
pyxiv/decorators.py
pyxiv/enums.py
pyxiv/exceptions.py
pyxiv/models.py
pyxiv/api/__init__.py
pyxiv/api/account.py
pyxiv/api/app.py
pyxiv/api/base.py
pyxiv/api/oauth.py
pyxiv/api/sketch.py
pyxiv-0.1.0.dist-info/DESCRIPTION.rst
pyxiv-0.1.0.dist-info/LICENSE.txt
pyxiv-0.1.0.dist-info/METADATA
pyxiv-0.1.0.dist-info/RECORD
pyxiv-0.1.0.dist-info/WHEEL
pyxiv-0.1.0.dist-info/metadata.json
pyxiv-0.1.0.dist-info/top_level.txt
