Metadata-Version: 2.0
Name: pyxiv
Version: 0.1.0
Summary: Pixiv Private API Wrapper
Home-page: https://github.com/cwkfr/pyxiv
Author: Arkie
Author-email: cwkfr@protonmail.com
License: MIT
Keywords: pixiv api anime manga
Platform: UNKNOWN
Classifier: Development Status :: 3 - Alpha
Classifier: License :: OSI Approved :: MIT License
Classifier: Programming Language :: Python
Classifier: Programming Language :: Python :: 3
Classifier: Programming Language :: Python :: 3.6
Classifier: Topic :: Software Development :: Libraries
Classifier: Topic :: Software Development :: Libraries :: Python Modules
Classifier: Topic :: Multimedia
Classifier: Topic :: Multimedia :: Graphics
Requires-Python: >=3.6.0
Requires-Dist: requests
Requires-Dist: decorator
Requires-Dist: uritemplate
